{
  "errata_id": "3ca67f19cf877919805c47582950d1bd9676892e9e1ecce845cd127c314a8b14",
  "attachments": [],
  "tags": [
    "lo:stax-anth:7-2-1",
    "assignment-type:homework",
    "book:stax-anth",
    "context-cnxmod:2b7645d9-177b-42bf-b595-adba152089a0",
    "book-slug:introduction-anthropology",
    "module-slug:introduction-anthropology:7-2-modes-of-subsistence"
  ],
  "books": [
    {
      "name": "stax-anth",
      "lo": [
        "7-2-1"
      ]
    }
  ],
  "context": [
    "m00043"
  ]
}